jupyterlab_cpg_portal/__init__.py
jupyterlab_cpg_portal/_version.py
jupyterlab_cpg_portal/labextension/package.json
jupyterlab_cpg_portal/labextension/schemas/jupyterlab_cpg_portal/package.json.orig
jupyterlab_cpg_portal/labextension/schemas/jupyterlab_cpg_portal/plugin.json
jupyterlab_cpg_portal/labextension/static/728.02c504d48e7408920f9e.js
jupyterlab_cpg_portal/labextension/static/739.0fd885ea1e12f21c0df4.js
jupyterlab_cpg_portal/labextension/static/remoteEntry.9f80efadf3093989aa14.js
jupyterlab_cpg_portal/labextension/static/style.js
jupyterlab_cpg_portal/labextension/static/third-party-licenses.json
jupyterlab_cpg_portal-0.1.11.data/data/share/jupyter/labextensions/jupyterlab_cpg_portal/package.json
jupyterlab_cpg_portal-0.1.11.data/data/share/jupyter/labextensions/jupyterlab_cpg_portal/schemas/jupyterlab_cpg_portal/package.json.orig
jupyterlab_cpg_portal-0.1.11.data/data/share/jupyter/labextensions/jupyterlab_cpg_portal/schemas/jupyterlab_cpg_portal/plugin.json
jupyterlab_cpg_portal-0.1.11.data/data/share/jupyter/labextensions/jupyterlab_cpg_portal/static/728.02c504d48e7408920f9e.js
jupyterlab_cpg_portal-0.1.11.data/data/share/jupyter/labextensions/jupyterlab_cpg_portal/static/739.0fd885ea1e12f21c0df4.js
jupyterlab_cpg_portal-0.1.11.data/data/share/jupyter/labextensions/jupyterlab_cpg_portal/static/remoteEntry.9f80efadf3093989aa14.js
jupyterlab_cpg_portal-0.1.11.data/data/share/jupyter/labextensions/jupyterlab_cpg_portal/static/style.js
jupyterlab_cpg_portal-0.1.11.data/data/share/jupyter/labextensions/jupyterlab_cpg_portal/static/third-party-licenses.json
jupyterlab_cpg_portal-0.1.11.data/data/share/jupyter/labextensions/jupyterlab_cpg_portal/install.json
jupyterlab_cpg_portal-0.1.11.dist-info/METADATA
jupyterlab_cpg_portal-0.1.11.dist-info/WHEEL
jupyterlab_cpg_portal-0.1.11.dist-info/licenses/LICENSE
jupyterlab_cpg_portal-0.1.11.dist-info/RECORD
