Metadata-Version: 2.4
Name: jupyterlab_cpg_portal
Version: 0.1.11
Summary: Access file in CPG Portal
Project-URL: Homepage, https://github.com/wytamma/jupyterlab-cpg-portal
Project-URL: Bug Tracker, https://github.com/wytamma/jupyterlab-cpg-portal/issues
Project-URL: Repository, https://github.com/wytamma/jupyterlab-cpg-portal
Author-email: jupyterlab-cpg-portal <wytamma.wirth@unimelb.edu.au>
License: BSD 3-Clause License
License-File: LICENSE
Keywords: jupyter,jupyterlab,jupyterlab-extension
Classifier: Framework :: Jupyter
Classifier: Framework :: Jupyter :: JupyterLab
Classifier: Framework :: Jupyter :: JupyterLab :: 4
Classifier: Framework :: Jupyter :: JupyterLab :: Extensions
Classifier: Framework :: Jupyter :: JupyterLab :: Extensions :: Prebuilt
Classifier: License :: OSI Approved :: BSD License
Classifier: Programming Language :: Python
Classifier: Programming Language :: Python :: 3
Classifier: Programming Language :: Python :: 3.9
Classifier: Programming Language :: Python :: 3.10
Classifier: Programming Language :: Python :: 3.11
Classifier: Programming Language :: Python :: 3.12
Classifier: Programming Language :: Python :: 3.13
Requires-Python: >=3.9
